{
  "source_file": "203_قانون مكافحة غسل الأموال وتمويل الإرهاب وتعديلاته.docx",
  "source_path": "C:\\Users\\LEGION\\Documents\\kimi\\workspace\\yemen_legal_docs_v5\\القوانين واللوائح المتضمنة نصوص عقابية\\203_قانون مكافحة غسل الأموال وتمويل الإرهاب وتعديلاته.docx",
  "converted_at": "2026-06-23T20:54:45.137366",
  "metadata": {
    "title": "قانون مكافحة غسل الأموال وتمويل الإرهاب وتعديلاته",
    "classification": "القوانين واللوائح المتضمنة نصوص عقابية",
    "number": "٢٠٣",
    "year": "٢٠١٠",
    "source_url": "http://agoyemen.net/lib_details.php?id=203",
    "preamble": "قانون رقم\n(١)\nلسنة\n٢٠١٠\nم\nبشأن مكافحة غسل الأموال وتمويل الإرهاب\nباسم الشعب\n:\nرئيس الجمهورية\n-\nبعد الإطلاع على دستور الجمهورية اليمنية\n.\nوبعد موافقة مجلس النواب\nأصدرنا القانون الآتي نصه"
  },
  "parts": [],
  "articles": [],
  "flat_articles": [
    {
      "number": "2",
      "title": "",
      "content": "مادة(٢) لأغراض تطبيق أحكام هذا القانون يقصد بالألفاظ والعبارات الواردة أدناه المعاني المبينة أمام كل منها ما لم يقتض سياق النص معنى آخر أو دلت القرينة على خلاف ذلك:\nالجمهورية :الجمهورية اليمنية.\nالبنك المركزي :البنك المركزي اليمني.\nالمحافظ :محافظ البنك المركزي اليمني.\nاللجنة :اللجنة الوطنية لمكافحة غسل الأموال وتمويل الإرهاب المشكلة بموجب أحكام هذا القانون.\nالوحدة : وحدة جمع المعلومات المالية.\nاللائحة :اللائحة التنفيذية لهذا القانون.\nالأموال :الأصول أياً كان نوعها مادية أو غير مادية, منقولة أو غير منقولة, التي يتحصل عليها بأي وسيلة كانت, والوثائق أو الصكوك القانونية أياً كان شكلها بما في ذلك الشكل الإلكتروني أو الرقمي والتي تدل على ملكية تلك الأموال أو مصلحه فيها.\nوتشمل على سبيل المثال العملات بجميع أنواعها المحلية والأجنبية, والأوراق المالية والتجارية والإعتمادات المصرفية والشيكات السياحية والحوالات المالية والأسهم والسندات والكمبيالات وخطابات الإعتماد أو أية فوائد أو أرباح أو عوائد من هذه الأموال أو القيمة المستحقة منها أو الناشئة عنها.\nالمتحصلات :الأموال الناتجة أو العائدة بطريقة مباشرة أو غير مباشرة من إرتكاب أى جريمة.\nغسل الأموال :الفعل المحدد في المادة (٣) من هذا القانون.\nتمويل الإرهاب :الفعل المحدد في المادة (٤) من هذا القانون.\nالمؤسسات المالية : أي موسسة مالية تمارس أياً من الأنشطة أو العمليات لصالح العملاء أو لحسابهم أياً كان شكلها القانوني سواءً كانت تتخذ شكل شركة أو منشأة فردية والتي تمارس أي من الأعمال التالية:\nأ- قبول الودائع بجميع أنواعها.\nب- منح الإئتمان بجميع أنواعه.\nج- التأجير التمويلي.\nد- تحويل الأموال.\nه- صرف العملات وإستبدالها.\nو- إصدار أدوات الدفع بكافة أنواعها ومن ذلك بطاقات الدفع والإئتمان والشيكات والصكوك وأي أعمال مصرفية أخرى منصوص عليها في القانون التجاري النافذ.\nز- الضمانات والتعهدات المالية بما في ذلك التمويل العقاري والتخصيم.\nح- التعامل في أدوات السوق النقدي وسوق رأس المال بيعاً وشراء بما في ذلك التعامل في العملات الأجنبية وفي أسواق الصرف الآنية والآجلة.\nط- التعامل في الأوراق المالية بما في ذلك أذون الخزانة.\nي- تقديم الخدمات الإدارية والإستشارية للمحافظ الإستثمارية وخدمات أمناء الإستثمار.\nك- إدارة وحفظ الأوراق المالية والأشياء الثمينة.\nل- التأمين على الحياة وأية منتجات تأمينية أخرى ذات عنصر إستثماري.\nم- الأنشطة المالية الأخرى التي يصدر بتحديدها قرار من رئيس مجلس الوزراء بناءً على إقتراح اللجنة.\nالمؤسسات غير المالية والمهن المُعيَّنة :\nأي مؤسسة تمارس أياً من الأنشطة أو العمليات التالية لصالح العملاء أو لحسابهم , أياً كان شكلها القانوني سواءً كانت تتخذ شكل شركة أو منشأة فردية وتشمل مايلي:\nأ- سمسرة العقارات\nب- تجارة المعادن الثمينة أو الأحجار الكريمة وكتاب وأمناء التوثيق.\nج- أعمال المحاماة أو المحاسبة من خلال مكاتب خاصة.\nد- خدمات تأسيس الشركات والأنشطة الملحقة بها.\nه- أي نشاط أو أنشطة أخرى يصدر بتحديدها قرار من رئيس مجلس الوزراء بناءًُ على إقتراح اللجنة.\nجهات الرقابة والإشراف : الجهات الآتية المنوط بها كل في نطاق إختصاصها صلاحية الإشراف والرقابة على أي من أنشطة المؤسسات المالية و المؤسسات غير المالية والمهن المعينة:\nأ- وزارة العدل.\nب- وزارة الشئون الإجتماعية والعمل.\nج- وزارة الصناعة والتجارة.\nد- وزارة الإتصالات وتقنية المعلومات.\nه- البنك المركزي اليمني.\nو- مصلحة الجمارك.\nز- الجهاز المركزي للرقابة والمحاسبة.\nح- الهيئة العامة للأراضي والمساحة والتخطيط العمراني.\nط- الهيئة العامة للمواصفات والمقاييس وضبط الجودة.\nي- أية جهة أخرى تخول صلاحية الرقابة والإشراف على أي من أنشطة المؤسسات المالية أو غير المالية والمهن المعينة بمقتضى قرار يصدر من رئيس مجلس الوزراء بناءً على إقتراح اللجنة.\nالمستفيد الحقيقي : الشخص الطبيعي صاحب الملكية أو السيطرة الفعلية على العميل أو الذي تتم العملية لحسابه أو لمصلحته أو وفقاً لإرادته.\nالأشخاص المعرضون سياسياً : أي شخص من الأشخاص الطبيعية الموكلة إليهم أو أوكلت إليهم مهام أو شغلوا وظائف عامة عليا في الجمهورية أو دولة أجنبية مثل رؤساء الدول أو الحكومات أو غيرهم من السياسيين رفيعي المستوى أو المسئولين الحكوميين أو القضائيين أو العسكريين أو كبار الموظفين التنفيذيين في الشركات والمؤسسات المملوكة للدولة أو مسؤولو الأحزاب السياسية الهامين أو الذين أوكلت إليهم منظمة إقليمية أو دولية وظيفة بارزة ويشمل ذلك أفراد عائلات هؤلاء الأشخاص أو شركائهم المقربين, ولا ينطبق هذا التعريف على الأشخاص الذين يشغلون مناصب متوسطة أو أقل في المؤسسات.\nالحجز :حظر إحالة الأموال أو الممتلكات الأخرى أو تحويلها أو التصرف فيها أو نقلها إستناداً إلى قرار صادر عن محكمة، ولمدة سريان ذلك القرار. وتبقى الأموال أو الممتلكات الأخرى المحجوزة ملكاً للأشخاص الذين كانت لهم مصلحة في تلك الأموال أو الممتلكات وقت الحجز، وتتولى إدارتها السلطة القضائية .\nالتجميد :حظر نقل الأموال أو الممتلكات أو المعدات أو الأدوات أو أي أصول أخرى، أو تحويلها أو التصرف فيها أو حركتها إستناداً إلى إجراء إتخذته سلطة مختصة، أو بناءً على قرار من سلطة قضائية مختصة بموجب آلية للتجميد طوال مدة سريان هذا الإجراء أو حتى يتم إجراء المصادرة وتظل الأموال أو الممتلكات أو المعدات أو الأدوات أو الأصول الأخرى المجمدة ملكاً للشخص الطبيعي أو الإعتباري أو للأشخاص الطبيعية أو الإعتبارية الذين كانت لهم مصلحة في تلك الأموال أو الممتلكات أو المعدات أو الأدوات المحددة وقت التجميد، ويجوز أن تظل إدارتها موكلة للمؤسسة المالية التي عينها ذلك الشخص الطبيعي أو الإعتباري أو الأشخاص الطبيعية أو الإعتبارية أو طرف ثالث بناءً على قرار من السلطة المختصة أو السلطة القضائية المختصة التي أصدرت قرار التجميد قبل إتخاذ إجراء بموجب آلية التجميد.\nالعميل العابر:العميل الذي لا تربطه علاقة مستمرة مع المؤسسة المالية أو المؤسسات غير المالية.\nالعلاقة المستمرة : كل علاقة مالية أو تجارية يتوقع عند نشأتها أن تمتد لفترة زمنية وأن تتضمن عمليات متعددة. وتشمل العلاقة المستمرة أي علاقة تجارية أو مهنية ذات صلة بأحد الأنشطة أو العمليات التي تمارسها المؤسسات المالية و المؤسسات غير المالية والمهن المعينة متى توقعت المؤسسة أن تمتد العلاقة لفترة من الزمن.\nالمصادرة :التجريد النهائي من الأموال أو الأصول أو الممتلكات الأخرى، بموجب حكم قضائي بات لصالح الدولة ويفقد الشخص الطبيعي أو الإعتباري أو الأشخاص الطبيعية\nأو الإعتبارية الاخرين جميع حقوق ملكية تلك الأموال أو الأصول أو الممتلكات الأخرى.\nالفعل\nالإرهابي : أ- أي فعل يشكل جريمة وفقاً لأي من الإتفاقيات التالية:\n١- إتفاقية قمع الإستيلاء غير المشروع على الطائرات (١٩٧٠).\n٢- إتفاقية قمع جرائم الإعتداء على سلامة الطيران المدني (١٩٧١).\n٣- إتفاقية منع ومعاقبة الجرائم التي ترتكب ضد الأشخاص المشمولين بالحماية بما فيهم الممثلين الدبلوماسيون (١٩٧٣).\n٤- الإتفاقية الدولية لمناهضة أخذ الرهائن (١٩٧٩).\n٥- إتفاقية الحماية المادية للمواد النووية (١٩٨٠).\n٦- البروتوكول المتعلق بقمع أعمال العنف غير المشروعة في المطارات التي تخدم الطيران المدني الدولي التكميلي لإتفاقية قمع الأعمال غير المشروعة الموجهة ضد سلامة الطيران المدني\n(١٩٨٨).\n٧- إتفاقية قمع الأعمال غير المشروعة الموجهة ضد سلامة الملاحة البحرية (١٩٨٨).\n٨- البروتوكول المتعلق بقمع الأعمال غير المشروعة ضد سلامة المنصات الثابتة القائمة في الجرف القاري (١٩٨٨).\n٩- الإتفاقية الدولية لقمع الهجمات الإرهابية بالقنابل (١٩٩٧).\n١٠-الإتفاقية الدولية لقمع تمويل الإرهاب (١٩٩٩).\nب- أي فعل آخر يهدف إلى التسبب في موت شخص مدني أو إصابته بجروح بدنية جسيمة, أو أي شخص آخر يكون غير مشترك بأعمال عدائية في حالة نشوب نزاع مسلح متى كان الغرض من هذا الفعل بطبيعته أو سياقه موجهاً لترويع السكان, أو إرغام حكومة أو منظمة دولية على القيام بعمل معين أو الإمتناع عن القيام به.\nالإرهابي : أي شخص طبيعي يقوم بأي من الأفعال التالية:\nأ- إرتكاب أو الشروع في إرتكاب أفعال إرهابية عمداً, بأي وسيلة, سواءً بشكل مباشر أو غير مباشر.\nب- الإشتراك كطرف في أفعال إرهابية.\nج- تنظيم أفعال إرهابية, أو توجيه الآخرين إلى إرتكابها.\nد- المساهمة في إرتكاب أفعال إرهابية, مع مجموعة من الأشخاص تعمل لغرض مشترك عمداً, وبهدف تعزيز الفعل الإرهابي أو مع العلم بنية المجموعة في إرتكاب فعل إرهابي.\nالمنظمة الإرهابية:\nأي جماعة من الإرهابيين تقوم بأي فعل من الأفعال التالية:\nأ- إرتكاب أو الشروع في إرتكاب أفعال إرهابية عمداً, بأي وسيلة, بشكل مباشر أو غير مباشر.\nب- الإشتراك في تنفيذ أفعال إرهابية.\nج- تنظيم أفعال إرهابية, أو توجيه الآخرين إلى إرتكابها.\nد- المساهمة في إرتكاب أفعال إرهابية, مع جماعة من الأشخاص تعمل لغرض مشترك عمداً, وبهدف تعزيز الفعل الإرهابي أو مع العلم بنية الجماعة في إرتكاب فعل إرهابي.",
      "part_number": null,
      "chapter_number": null,
      "division_number": null,
      "subdivision_number": 9
    },
    {
      "number": "3",
      "title": "",
      "content": "مادة (٣) أ- يُعد مرتكباً لجريمة غسل الأموال كل من يأتي فعلاً من الأفعال الآتية سواءً وقع الفعل داخل أو خارج الجمهورية:\n١- تحويل أو نقل أموال من قِبل أي شخص يعلم أو كان ينبغي أن يعلم بأنها عائدات أو متحصلات إجرامية بغرض إخفاء أو تمويه المصدر غير المشروع لتلك الأموال، أو قصد مساعدة أي شخص ضالع في إرتكاب الجريمة الأصلية التي نتجت منه، على الإفلات من العواقب القانونية لأفعاله.\n٢- إخفاء أو تمويه الطبيعة الحقيقية للأموال أو مصدرها أو مكانها أوكيفية التصرف فيها أو حركتها أو ملكيتها أو الحقوق المتعلقة بها من قِبل شخص يعلم أو كان ينبغي أن يعلم بأنها عائدات أو متحصلات إجرامية.\n٣- إكتساب أو حيازة أو إستخدام الأموال من قِبل أي شخص يعلم أو كان ينبغي أن يعلم وقت تسلمها بأنها عائدات أو متحصلات إجرامية. ويمكن إستخلاص العلم المشار إليه في بنود الفقرة (أ) من هذه المادة من الظروف الواقعية الموضوعية.\nب- كما يُعد مرتكباً لجريمة غسل الأموال كل من شرع أو شارك أو حرض\nأو أمر أو تواطأ أو تآمر أو قدم مشورة أو ساعد على إرتكاب أي من الأفعال الواردة في البنود(١ ، ٢ ، ٣) من الفقرة (أ) من هذه المادة.\nج- تعتبر الأفعال المحددة في البنود (١ ، ٢ ، ٣) من الفقرة (أ) من هذه المادة جرائم غسل أموال وذلك متى كانت هذه الأموال متحصلة من جريمة من الجرائم الأصلية التالية:\n١- المشاركة في جماعة إجرامية منظمة.\n٢- الإرهاب بما في ذلك تمويل الإرهاب.\n٣- الرق والإتجار بالبشر وتهريب المهاجرين.\n٤- الإستغلال الجنسي بما في ذلك الإستغلال الجنسي للأطفال.\n٥- زراعة وتصنيع المواد المخدرة والمؤثرات العقلية والإتجار غير المشروع فيها.\n٦- الإتجار غير المشروع بالأسلحة والذخائر.\n٧- الإتجار بالسلع المسروقة والإتجار غير المشروع بالسلع الأخرى.\n٨- الفساد والرشوة.\n٩- النصب والإحتيال والغش.\n١٠- التزوير والتزييف بما فيها تزوير المحررات الرسمية والعرفية، وتزييف العملات وترويج عملة مزيفة أو غير متداولة، وتزييف البضائع والقرصنة عليها وتزييف الأختام والعلامات الرسمية والأسناد العامة وما في حكمها وتزييف العلامات التجارية.\n١١- جرائم البيئة.\n١٢-القتل وإحداث جروح جسدية جسيمة.\n١٣-خطف وأخذ واحتجاز الرهائن وتقييد حرياتهم.\n١٤- السطو والسرقة والإستيلاء على أموال عامة أو خاصة.\n١٥-التهريب بما فيها التهريب الجمركي والتهرب الضريبي وتهريب الآثار والمخطوطات التاريخية.\n١٦-الجرائم الضريبية .\n١٧-الإبتزاز.\n١٨-القرصنة.\n١٩-التحايل والتستر التجاري والتلاعب بالأسواق بما في ذلك الأسواق المالية والإتجار في أدواتها من قِبل المطلعين بناءً على معلومات غير معلنة.\n٢٠- الجرائم الماسة بالإقتصاد الوطني المنصوص عليها في قانون الجرائم والعقوبات.\n٢١- كافة الجرائم التي لم يرد ذكرها أعلاه و المعاقب عليها بمقتضى أحكام القوانين النافذة.\nد- تشمل الجرائم الأصلية المبينة في الفقرة (أ) من هذه المادة الجرائم الأصلية التي ترتكب خارج الجمهورية إذا كانت تشكل جريمة وفقاً لقانون الدولة التي أرتكبت فيها وتشكل في ذات الوقت جريمة وفقاً للقوانين النافذة في الجمهورية.\nه- تعتبر جريمة غسل الأموال جريمة مستقلة عن الجريمة الأصلية المتحصل منها المال, ولايشترط حصول إدانة بإرتكاب الجريمة الأصلية لإثبات المصدر غير المشروع لمتحصلات الجريمة.",
      "part_number": null,
      "chapter_number": null,
      "division_number": null,
      "subdivision_number": 9
    },
    {
      "number": "4",
      "title": "",
      "content": "مادة (٤) يُعد مرتكباً لجريمة تمويل الإرهاب كل من:\nأ- يجمع أو يقدم أموالاً أو يؤمِّن الحصول عليها أو ينقلها عمداً وبإرادته بأي وسيلة كانت بطريقة مباشرة أو غير مباشرة وسواءً كانت من مصادر مشروعة أو غير مشروعة بنية إستخدامها أو مع علمه بأنها ستقدم لمنظمة إرهابية أو هيئة أو جمعية إرهابية أو لإرهابي أو لفعل إرهابي, ويمكن إستنتاج العلم من الظروف الواقعية الموضوعية, وتبقى المسئولية الجنائية قائمة سواءً أُستخدمت هذه الأموال كلياً أو جزئياً أو لم تستخدم وسواءً وقعت هذه الأفعال داخل الجمهورية أو خارجها.\nب- يشرع أو يشارك أو يحرض أو يأمر أو يتواطأ أو يتآمر أو يقدم مشورة أو يساعد على إرتكاب أي من الأفعال الواردة في الفقرة (أ) من هذه المادة.\nج- ينظم إرتكاب جريمة من الجرائم المنصوص عليها في الفقرة(أ) أو الفقرة (د) من هذه المادة.\nد- يشارك في قيام مجموعة من الأشخاص بقصد مشترك بإرتكاب جريمة واحدة أو أكثر من الجرائم المشار إليها في الفقرة (أ) من هذه المادة وتكون هذه المشاركة عمدية وتنفذ بهدف :\n١- توسيع النشاط الجنائي أو الغرض الجنائي للمجموعة عندما ينطوي ذلك النشاط أو الغرض على إرتكاب جريمة من الجرائم المشار إليها في الفقرة (أ) من هذه المادة.\n٢- إرتكاب جريمة من الجرائم المشار اليها في الفقرة (أ) من هذه المادة.",
      "part_number": null,
      "chapter_number": null,
      "division_number": null,
      "subdivision_number": 9
    },
    {
      "number": "10",
      "title": "",
      "content": "مادة (١٠) تلتزم المؤسسات المالية و المؤسسات غير المالية والمهن المعينة بإتخاذ الإجراءات التالية:\nأ- تصنيف عملائها وخدماتها بحسب درجة مخاطر غسل الأموال وتمويل الإرهاب وإتخاذ التدابير الكافية لمعالجة تلك المخاطر وعليها أن تبذل عناية خاصة في التعامل مع الحالات التي تمثل درجة مخاطر مرتفعة\nبما في ذلك:\n١- المعاملات غير المعتادة والتي ليس لها مبرر إقتصادي.\n٢- المعاملات والأشخاص المرتبطون بدول لا تُطبِّق إجراءات فعالة في مكافحة غسل الأموال وتمويل الإرهاب وفقاً للمبادئ والمعايير الدولية.\nوتبين اللائحة الضوابط التي يتعين إتباعها في تصنيف العملاء و بذل العناية الخاصة.\nب- فحص وبحث خلفية المعاملات الكبيرة والمعقدة والتأكد من الغرض منها وتسجيلها وإتاحتها للسلطات المختصة عند الإقتضاء ومدققي الحسابات لمدة خمس سنوات على الأقل.\nج- إتخاذ التدابير اللازمة لمنع سوء إستخدام التطورات التكنولوجية في مجال غسل الأموال و تمويل الإرهاب.\nد- وضع نُظم مناسبة لإدارة المخاطر لتحديد ما إذا كان العميل المستقبلي، أو العميل أو المستفيد الحقيقي شخصاً معرضاً سياسياً, فإذاتبين لها أنه كذلك فيتعين إتخاذالإجراءات التالية :\n١- الحصول على موافقة الإدارة العليا قبل إنشاء علاقة عمل مع العميل أو الإستمرار فيها\n٢- إتخاذ التدابير اللازمة لمعرفة وتحديد مصدر ثروته والتعرف على المستفيد الحقيقي لأمواله.\n٣- مراقبة علاقة العمل بصورة مستمرة ومكثفة.\nه- وضع السياسات والإجراءات والضوابط الداخلية لمكافحة غسل الأموال وتمويل الإرهاب وتطبيقها على العملاء الحاليين والعملاء الجدد وإبلاغ موظفيها بها وتدريبهم عليها والتأكد من تطبيقها.",
      "part_number": null,
      "chapter_number": null,
      "division_number": null,
      "subdivision_number": 9
    },
    {
      "number": "13",
      "title": "",
      "content": "مادة (١٣) يجب على المؤسسات المالية والمؤسسات غير المالية والمهن المعينة التي تشتبه أو تتوفر لديها أسباب معقولة للإشتباه في أن أموالاً أو ممتلكات لها صلة أو إرتباط بغسل أموال أو أنها تشكل عائدات للجرائم الأصلية الواردة في المادة (٣) من هذا القانون أو أن لها صلة أو إرتباط بالإرهاب أو الأفعال الإرهابية أو تمويل الإرهاب أو أنها ستستخدم في القيام بأفعال إرهابية أو من جانب منظمات إرهابية أو ممن يمولون الإرهاب, أن تبلغ الوحدة فوراً عن هذه العمليات سواءً تمت أم لم تتم ، وتبين اللائحة الضوابط والإجراءات المتعلقة بهذا الإلتزام.",
      "part_number": null,
      "chapter_number": null,
      "division_number": null,
      "subdivision_number": 9
    },
    {
      "number": "17",
      "title": "",
      "content": "مادة (١٧) أ- على وزارة الخارجية موافاة النائب العام بالقوائم الصادرة عن لجنة عقوبات القاعدة وطالبان المنشأة بموجب قرار مجلس الأمن رقم (١٢٦٧) (١٩٩٩م) والقرارات اللاحقة له والمتعلقة بتحديد الأشخاص والكيانات فور صدورها.\nب- يصدر النائب العام فور تلقيه القوائم من وزارة الخارجية القرارات اللازمة بتجميد أموال وأصول وممتلكات الأشخاص والكيانات الذين تحددهم اللجنة المنشأة بموجب قرار مجلس الأمن رقم (١٢٦٧) (١٩٩٩م) والقرارات اللاحقة له بما في ذلك الأموال المستمدة من أموال أو اصول أخرى أو المتولدة عنها مملوكة أو خاضعة بصورة مباشرة أو غير مباشرة لهم أو لأشخاص يعملون بإسمهم أو بتوجيه منهم, وسواءً كانت هذه الأموال لدى مؤسسات مالية أومؤسسات غير مالية أومهن معينه أو لدى أشخاص طبيعية أو إعتبارية أخرى, مع مراعاة حقوق الغير حسن النية, وعلى جهات الرقابة والإشراف تعميم هذه القرارات على المؤسسات المالية وغير المالية والمهن المعينة والأشخاص الطبيعية والإعتبارية.\nج- على المؤسسات المالية وغير المالية والمهن المعينة والأشخاص الطبيعية والإعتبارية تجميد تلك الأموال أو الأصول أو الممتلكات الأخرى فوراً وبدون إشعار مسبق للأشخاص أو الكيانات الصادرة بحقهم قرارات التجميد, وإبلاغ الوحدة بالأموال والأصول والممتلكات المجمدة وفقاً لأحكام هذه المادة, وتحدد اللائحة آلية التجميد والإجراءات المنظمة لذلك.\nد- تتولى جهات الرقابة والإشراف التأكد من إلتزام المؤسسات المالية والمؤسسات غير المالية بتنفيذ قرارات النائب العام الصادرة وفقاً لأحكام الفقرة (ب) من هذه المادة.\nه- للمتضرر من قرارات التجميد أو الحجز المشار إليها في هذه المادة إتباع كافة الوسائل المتاحة الدبلوماسية أو القانونية أو القضائية لإلغاء التجميد أو الحجز أو حذف الإسم من القائمة بما يتماشى مع الإلتزامات الدولية للجمهورية, وللأشخاص الذين تأثروا دون قصد بإجراءات التجميد أو الحجز دون أن يكونوا هم الأشخاص أو الكيانات المحددة في تلك القوائم إتباع تلك الوسائل المتاحة.\nوتبين اللائحة الإجراءات الملائمة للترخيص بإستخدام الأموال أو الأصول أو الممتلكات الأخرى التي جمدت بموجب أحكام هذه المادة وذلك للإستخدامات الضرورية لتغطية النفقات الأساسية أو دفع أنواع معينة من الرسوم أو نفقات أو رسوم خدمات أو نفقات غير عادية.",
      "part_number": null,
      "chapter_number": null,
      "division_number": null,
      "subdivision_number": 9
    },
    {
      "number": "26",
      "title": "",
      "content": "مادة(٢٦) أ- تنشأ بموجب أحكام هذا القانون لجنة تُسمى (اللجنة الوطنية لمكافحة غسل الأموال وتمويل الإرهاب) تتبع رئيس مجلس الوزراء ويكون مقرها العاصمة صنعاء.\nب- تتمتع اللجنة بالشخصية الإعتبارية والذمة المالية المستقلة.\nج- تشكل اللجنة بقرار من رئيس مجلس الوزراء بناءً على عرض وزير المالية وتتكون من ممثل واحد من الجهات التالية بناءً على ترشيحها:\n١- وزارة المالية رئيساً للجنة.\n٢- البنك المركزي نائباً للرئيس.\n٣- وزارة العدل عضواً.\n٤- وزارة الداخلية عضواً.\n٥- وزارة الخارجية عضواً.\n٦- وزارة الصناعة والتجارة عضواً.\n٧- وزارة الشئون الإجتماعية والعمل عضواً.\n٨- وزارة الإتصالات وتقنية المعلومات عضواً.\n٩- جهاز الأمن السياسي عضواً.\n١٠-جهاز الأمن القومي عضواً.\n١١- الجهاز المركزي للرقابة والمحاسبة عضواً.\n١٢-النيابة العامة عضواً.\n١٣-الهيئة الوطنية العليا لمكافحة الفساد عضواً.\n١٤- الهيئة العامة للإستثمار عضواً.\n١٥-الهيئة العامة للأراضي والمساحة والتخطيط العمراني عضواً.\n١٦-مصلحة الجمارك عضواً.\n١٧-وحدة جمع المعلومات المالية عضواً.\n١٨-جمعية البنوك عضواً.\n١٩-الإتحاد العام للغرف التجارية الصناعية عضواً.\nد- تختار اللجنة أحد أعضاءها مقرراً لها.\nه- للجنة الإستعانة بمن تراه من الخبراء والفنيين.",
      "part_number": null,
      "chapter_number": null,
      "division_number": null,
      "subdivision_number": 9
    },
    {
      "number": "27",
      "title": "",
      "content": "مادة (٢٧) تتولى اللجنة ممارسة الإختصاصات والمهام الآتية:\nأ- وضع إستراتيجية وطنية لمكافحة غسل الأموال وتمويل الإرهاب.\nب- إقتراح السياسات الخاصة بمكافحة غسل الأموال وتمويل الإرهاب ورفعها إلى مجلس الوزراء لإقرارها.\nج- دراسة ومتابعة التطورات الدولية في مجال مكافحة غسل الأموال وتمويل الإرهاب وتقديم التوصيات بشأن تطوير التعليمات والأنظمة والإجراءات الصادرة عن جهات الرقابة والإشراف في الجمهورية وإقتراح التعديلات التشريعية بما يتلائم مع هذه التطورات.\nد- العمل على رفع الوعي بمخاطر غسل الأموال وتمويل الإرهاب.\nه- تنسيق جهود الجهات الممثلة في اللجنة.\nو- تنظيم وإقامة الندوات وورش العمل المتعلقة بمكافحة غسل الأموال وتمويل الإرهاب.\nز- تمثيل الجمهورية في المحافل الدولية والمشاركة في الإجتماعات والمؤتمرات المتعلقة بمكافحة غسل الأموال وتمويل الإرهاب.\nح- وضع وإقرار اللائحة الداخلية لعمل اللجنة.\nط- مناقشة موازنة اللجنة ورفعها للجهات المختصة لإدراجها ضمن الموازنة العامة للدولة.",
      "part_number": null,
      "chapter_number": null,
      "division_number": null,
      "subdivision_number": 9
    },
    {
      "number": "31",
      "title": "",
      "content": "مادة (٣١) تختص الوحدة بالمهام التالية:\nأ- تلقي وتحليل الإخطارات الواردة من المؤسسات المالية والمؤسسات غير المالية والمهن المعينة والجهات الرقابية والإشرافية عن العمليات التي يشتبه في أنها تتضمن غسل أموال أو تمويل إرهاب أو أي من الجرائم الأصلية المرتبطة بها, وإحالة نتيجة تحليل الإخطارات للجهات المعنية للتصرف فيها عند الإقتضاء.\nب-إنشاء قاعدة بيانات لما يتوفر لديها من معلومات وإتاحتها للنيابة العامة وفقاً لأحكام قانون الإجراءات الجزائية.\nج- طلب أية معلومات إضافية تعتبرها مفيدة للقيام بوظيفتها متى كانت مرتبطة بأية معلومات سبق أن تلقتها أثناء مباشرة إختصاصاتها أو بناءً على طلب تتلقاه من الوحدات النظيرة في الدول الأخرى، ويتعين على الملتزمين بواجب الإخطار أن يزودوا الوحدة بتلك المعلومات خلال مدة لا تجاوز أسبوعاً من تاريخ طلبها ما لم تحدد الوحدة مدة أخرى، وعلى النموذج الذي تقره الوحدة، وفي الأحوال الطارئة يجوز للوحدة أن تحدد مدة أقصر وفقا للضوابط التي تبينها اللائحة.\nد- إبلاغ النيابة العامة بما تسفر عنه نتيجة تحليل الإخطارات, عندما تتوفر لديها مؤشرات جدية عن وجود شبهة غسل أموال أو تمويل إرهاب أو أي من الجرائم الأصلية المرتبطة بها مشفوعة بالإستدلالات اللازمة بشأنها.\nه-\nالطلب من الجهات التالية معلومات إضافية تتعلق بالإخطارات التي تتلقاها متى إعتبرتها مفيدة للقيام بوظيفتها أو بناءً على طلب تتلقاه من وحدة نظيرة\n١- جهات الرقابة والإشراف.\n٢- أي جهات حكومية أخرى.\nوعلى الجهات المشار إليها تزويد الوحدة بالمعلومات خلال مدة لا تجاوز أسبوعين من تاريخ طلبها.\nو- إخطار اللجنة وجهات الرقابة والإشراف المعنية بأي إخلال بأحكام هذا القانون يقع من المؤسسات المالية والمؤسسات غير المالية والمهن المعينة التي تخضع لأحكام هذا القانون.\nز- نشر تقارير دورية عن أنشطتها تتضمن على الأخص بيانات إحصائية ودراسات تحليلية في مجال مكافحة غسل الأموال وتمويل الإهارب.\nح- النزول الميداني للجهات والمؤسسات المشمولة في هذا القانون للتحقق من مدى إلتزامها بأحكام هذا القانون ولائحته.\nط- المشاركة في الندوات وورش العمل والمؤتمرات والإجتماعات الدولية والإقليمية ذات العلاقة بإختصاصها .",
      "part_number": null,
      "chapter_number": null,
      "division_number": null,
      "subdivision_number": 9
    },
    {
      "number": "32",
      "title": "",
      "content": "مادة(٣٢) أ- يكون للوحدة من تلقاء نفسها أو بناءً على طلب من الوحدات النظيرة في الدول الأخرى حق تبادل المعلومات معها متى كانت ملتزمة بقواعد السرية وبشرط المعاملة بالمثل ، ولا يجوز أن تستخدم تلك المعلومات إلا في الأغراض المتعلقة بمكافحة غسل الأموال وتمويل الإرهاب وبشرط الحصول على موافقة الجهات المقدمة لتلك المعلومات.\nب- لغرض الفقرة (أ) يجوز للوحدة إبرام مذكرات تفاهم مع وحدات أجنبية نظيرة تؤدي وظائف مماثلة وتخضع لإلتزامات مماثلة بشأن السرية.",
      "part_number": null,
      "chapter_number": null,
      "division_number": null,
      "subdivision_number": 9
    },
    {
      "number": "33",
      "title": "",
      "content": "مادة(٣٣) تتلقى النيابة العامة مباشرة أو عبر الطرق الدبلوماسية المعلومات المبلغة من أي دولة من الدول والتي تفيد بقيام شخص مقيم أو موجود في الجمهورية بإرتكاب أي من الجرائم المنصوص عليها في هذا القانون والتحقيق فيها وفقاً للقوانين النافذة وأحكام هذا القانون.",
      "part_number": null,
      "chapter_number": null,
      "division_number": null,
      "subdivision_number": 9
    },
    {
      "number": "35",
      "title": "",
      "content": "مادة(٣٥) أ- مع مراعاة ما تنص عليه الإتفاقيات الثنائية أو متعددة الأطراف المتعلقة بتبادل المساعدات القانونية والتي تكون الجمهورية طرفاً فيها، تقدم طلبات المصادرة المتعلقة كلياً أو جزئياً بجريمة غسل أموال أو تمويل إرهاب إلى السلطة القضائية المختصة عن طريق القنوات الدبلوماسية.\nب- لا تتم المصادرة إلا بصدور حكم قضائي بات.\nج- يجب أن يتضمن طلب المساعدة المتبادلة بالإضافة للمعلومات المنصوص عليها في الفقرة (ج) من المادة (٣٤) من هذا القانون صورة رسمية من الحكم البات الصادر بالمصادرة. ويجوز طلب معلومات إضافية من الدولة الطالبة للمساعدة القانونية لغرض تنفيذ الحكم. وفي كل الأحوال لا تُمكّن الدولة الطالبة للمصادرة من تلك الأموال أو عوائدها إلا بعد توقيع إتفاق ثنائي مع الدولة المطالبة حول إقتسام هذه الأموال.",
      "part_number": null,
      "chapter_number": null,
      "division_number": null,
      "subdivision_number": 9
    },
    {
      "number": "40",
      "title": "",
      "content": "مادة (٤٠) للنيابة العامة أثناء التحقيق أو بناءً على طلب الوحدة أو الجهة المختصة إصدار قرارات أو أوامر مؤقتة بالحجز التحفظي أو التجميد للأموال أو الأصول الآتية:\nأ- الممتلكات المغسولة.\nب- المتحصلات والأدوات التي أٌستخدمت أو المعدة للإستخدام في غسل الأموال والجرائم الأصلية.\nج- الممتلكات المتحصلة أو المستخدمة أو المعدة أو التي خصصت للإستخدام في الأفعال الإرهابية أو تمويل الإرهاب أو المنظمات الإرهابية.\nد- ممتلكات معادلة في القيمة للأموال أو الأصول الواردة في الفقرات\n(أ, ب, ج) من هذه المادة ، وذلك لمنع الإتجار بها أو نقلها أو التصرف فيها, مع مراعاة حقوق الغير حسن النية.",
      "part_number": null,
      "chapter_number": null,
      "division_number": null,
      "subdivision_number": 9
    },
    {
      "number": "41",
      "title": "",
      "content": "مادة (٤١) أ- يعاقب بالسجن مدة لا تزيد على سبع سنوات كل من إرتكب جريمة غسل أموال المنصوص عليها في المادة (٣) من هذا القانون.\nب- يعاقب بالسجن مدة لا تزيد على عشر سنوات كل من إرتكب جريمة تمويل الإرهاب المنصوص عليها في المادة (٤) من هذا القانون.\nج- في حال الإدانة بإرتكاب أي جريمة من الجرائم المبينة في المادتين ( ٣ ، ٤ ) من هذا القانون أو أي جريمة أصلية، ومع عدم الإخلال بحقوق الغير حسن النية، تصدر المحكمة المختصة حكماً بمصادرة:\n١- الأموال التي تشكل متحصلات جريمة بما فيها المتحصلات التي إختلطت بممتلكات أخرى، أو ممتلكات تعادل قيمة تلك المتحصلات.\n٢- الأموال التي تشكل موضوع الجريمة.\n٣- الأموال التي تشكل عائدات ومنافع أخرى متأتية من تلك الأموال أو الممتلكات أو من متحصلات الجريمة.\n٤- وسائط وأدوات إرتكاب الجريمة.\n٥- الأموال المشار إليها في الفقرات السابقة من هذه المادة ، والتي تم التصرف فيها إلى أي طرف، إلا إذا تبين للمحكمة أنه قد إكتسبها مقابل دفع ثمن مناسب أو حصل عليها مقابل تقديمه خدمات تتناسب مع قيمتها أو بناءً على أسباب مشروعة أخرى، وأنه كان يجهل مصدرها غير المشروع. وتكون المصادرة بموجب حكم قضائي بات لمصلحة الخزينة العامة للدولة.\nد- للمحكمة الحكم بأي عقوبة تكميلية وفقاً للقوانين النافذة.\nوتضاعف العقوبات المنصوص عليها في الفقرتين (أ , ب) من هذه المادة إذا أُرتكبت الجريمة من خلال جماعة إجرامية منظمة أو من خلال منظمة إرهابية أو إذا أُرتكبت الجريمة كجزء من أعمال إجرامية أخرى أو إستغلال للسلطات أو النفوذ.",
      "part_number": null,
      "chapter_number": null,
      "division_number": null,
      "subdivision_number": 9
    },
    {
      "number": "43",
      "title": "",
      "content": "مادة (٤٣) أ- يعاقب بالحبس مدة لاتزيد على ثلاث سنوات أو بالغرامة التي لاتزيد على عشرة ملايين ريال كل من يخالف أحكام المواد (٦, ١٣, ١٥, ١٧ فقرة (ج), ١٧ مكرر فقرة (ج), ١٨, ٢٠, ٢٣, ٢٥) من هذا القانون.\nب- يعاقب بالحبس مدة لاتزيد على سنتين أو بالغرامة التي لاتزيد على خمسة ملايين ريال كل من يخالف أحكام المادتين (١٢, ٣١ فقرة (ج))\nج- يعاقب بالحبس مدة لاتزيد على سنة أو بالغرامة التي لاتزيد على مليون ريال كل من يخالف أحكام المواد (٧, ٨, ٩, ١٠, ١١) من هذا القانون.\nد- إضافة إلى العقوبات الواردة في الفقرات (أ, ب, ج) من هذه المادة يجوز للمحكمة الحكم بإحدى العقوبات التكميلية الآتية:\n١- الغاء الترخيص.\n٢- المنع من مزاولة المهنة أو النشاط.\n٣- تغيير المدراء أو تقييد صلاحياتهم.\n٤- نشر الحكم الصادر بشأنه.\n٥- أي عقوبات تكميلية أخرى.",
      "part_number": null,
      "chapter_number": null,
      "division_number": null,
      "subdivision_number": 9
    },
    {
      "number": "2",
      "title": "",
      "content": "المادة (٢) تُضاف المواد التالية إلى القانون رقم(١)لسنة ٢٠١٠م بشأن مكافحة غسل الأموال وتمويل الإرهاب :",
      "part_number": null,
      "chapter_number": null,
      "division_number": null,
      "subdivision_number": 9
    },
    {
      "number": "17",
      "title": "",
      "content": "مادة (١٧ مكرر) أ- تتولى الجهات المختصة بمكافحة الإرهاب إعداد قوائم بأسماء الأشخاص والكيانات الذين يرتكبون أعمال إرهابية أو يحاولون إرتكابها أو يشاركون أو يسهلون إرتكابها بموجب القوانين النافذة وقرار مجلس الأمن رقم (١٣٧٣) (٢٠٠١) والقرارات اللاحقة له.\nب- يصدر النائب العام قرارات بتجميد أموال وممتلكات وأصول الأشخاص والكيانات المحددة أسمائهم بالقوائم وفقاً لنص الفقرة (أ) من هذه المادة, بما في ذلك الأموال المستمدة من أموال أو أصول أخرى أو المتولدة عنها مملوكة أو خاضعة بصورة مباشرة أو غير مباشرة لهم أو لأشخاص يعملون بإسمهم أو بتوجيه منهم وسواءً كانت هذه الأموال لدى مؤسسات مالية أو غير مالية أو مهن معينة أو لدى أشخاص طبيعية أو إعتبارية, ويراعى في ذلك حقوق الغير حسن النية, وعلى جهات الرقابة والإشراف تعميم هذه القرارات على المؤسسات المالية وغير المالية والمهن المعينة والأشخاص الطبيعية والإعتبارية.\nج- على المؤسسات المالية وغير المالية والمهن المعينة والأشخاص الطبيعية والإعتبارية تجميد تلك الأموال أو الأصول أو الممتلكات الأخرى فوراً وبدون إشعار مسبق للأشخاص أو الكيانات الصادرة بحقهم قرارات التجميد, وإبلاغ الوحدة بالأموال والأصول والممتلكات المجمدة وفقاً لأحكام هذه المادة.\nد- تتولى جهات الرقابة والإشراف التأكد من إلتزام المؤسسات المالية وغير المالية بتنفيذ قرارات النائب العام الصادرة وفقاً لأحكام الفقرة (ب) من هذه المادة.\nه- للمتضرر من قرارات التجميد أو الحجز المشار إليها في هذه المادة التظلم من قرار النائب العام أمام المحكمة المختصة خلال ٣٠ يوماً من تاريخ علمه بقرار التجميد.\nو- وتحدد اللائحة آلية التجميد والإجراءات المنظمة لذلك.",
      "part_number": null,
      "chapter_number": null,
      "division_number": null,
      "subdivision_number": 9
    },
    {
      "number": "17",
      "title": "",
      "content": "مادة (١٧) مكرر (١) أ- يتلقى النائب العام طلبات التجميد المقدمة من أي دولة والمتعلقة بتجميد أموال أو ممتلكات أو أصول أخرى لأشخاص مقيمين على أراضي الجمهورية, ويقوم النائب العام بدراسة هذه الطلبات والبت فيها وفي حالة الموافقة يصدر قراراً بتجميد تلك الأموال أو الممتلكات أو الأصول.\nب- تسري أحكام الفقرات (ج, د, ه) من المادة (١٧) مكرر بشأن التزامات المؤسسات المالية وغير المالية والمهن المعينة وجهات الرقابة والإشراف في تنفيذ قرار التجميد الصادر بموجب الفقرة (أ) من هذه المادة والتظلم منه.\nج- وتحدد اللائحة الأسس اللازمة للتعامل مع الطلبات المقدمة من أي دولة بشأن تجميد الأموال والممتلكات.",
      "part_number": null,
      "chapter_number": null,
      "division_number": null,
      "subdivision_number": 9
    },
    {
      "number": "26",
      "title": "",
      "content": "مادة (٢٦ مكرر) لايجوز رفع الدعوى الجزائية أو المدنية أو الإدارية ضد رئيس اللجنة أو أي من أعضاءها أو العاملين بها أو رئيس الوحدة أو أي من أعضاءها أو العاملين بها أو إتخاذ أي إجراء قانوني ضدهم وذلك بسبب القيام بالمهام المسندة إليهم بمقتضى هذا القانون.",
      "part_number": null,
      "chapter_number": null,
      "division_number": null,
      "subdivision_number": 9
    },
    {
      "number": "41",
      "title": "",
      "content": "مادة (٤١ مكرر) في حال وقوع جريمة معاقب عليها بموجب أحكام هذا القانون، وعدم إدانة فاعلها لوفاته أو لأنه مجهول الهوية، يحق للنيابة العامة أن ترفع الموضوع للمحكمة المختصة لإصدار حكم بمصادرة الأموال المتحصلة منها إذا قدمت أدلة كافية أنها متحصلات الجريمة, وفي جميع الأحوال ينبغي أن يحدد حكم المصادرة الأموال المعنية، وأن يتضمن التفاصيل اللازمة لتحديدها وتعيين موقعها.",
      "part_number": null,
      "chapter_number": null,
      "division_number": null,
      "subdivision_number": 9
    },
    {
      "number": "44",
      "title": "",
      "content": "مادة (٤٤ مكرر) أ- يعاقب بغرامة لاتقل عن خمسة ملايين ريال كل شخص إعتباري إرتكب جريمة غسل الأموال أو تمويل الإرهاب لصالحه أو بإسمه من قِبل شخص طبيعي يشغل موقعاً قيادياً فيه أو لديه تفويض بإتخاذ القرارات نيابة عنه أو مخول بممارسة السلطة فيه, وذلك بصرف النظر عما إذا أُدين الشخص الطبيعي بإرتكاب الجريمة من عدمه.\nب- لا تمنع العقوبة المقررة للشخص الإعتباري وفقاً للفقرة (أ) من هذه المادة من معاقبة الشخص الطبيعي المسؤول عن الإدارة الفعلية للشخص الإعتباري المخالف بذات العقوبات المقررة عن الأفعال التي ترتكب بالمخالفة لأحكام هذا القانون إذا ثبت علمه بها أو كانت الجريمة قد وقعت بسبب إخلاله بواجبات وظيفته أو إذا كان ناتجاً عن إهماله واجبات الوظيفة.\nج- يجوز للمحكمة الحكم على الشخص الإعتباري بإحدى العقوبات التكميلية التالية:\n١- وقف مزاولة المهنة أو النشاط.\n٢- الغاء ترخيص مزاولة المهنة أو النشاط.\n٣- اغلاق محل مزاولة المهنة أو النشاط أو المرافق التابعة له التي أُستخدمت في إرتكاب الجريمة بصفة دائمة أو مؤقتة.\n٤- تصفية أعماله.\n٥- وضعه تحت الحراسة القضائية وفقاً لأحكام القوانين النافذة.\n٦- نشر حكم الإدانة الصادر بشأنه.",
      "part_number": null,
      "chapter_number": null,
      "division_number": null,
      "subdivision_number": 9
    },
    {
      "number": "3",
      "title": "",
      "content": "المادة (٣) تحذف الفقرة (أ) من المادة (٣٤) من القانون رقم(١)لسنة ٢٠١٠م بشأن مكافحة غسل الأموال وتمويل الإرهاب.\nالمادة (٤) يُعمل بهذا القانون من تاريخ صدوره وينشر في الجريدة الرسمية.\nصدر برئاسة الجمهورية بصنعاء\nبتاريخ ٦ / ذو القعدة /١٤٣٤ه\nالموافق ١٢ / سبتمبر /٢٠١٣م\nعبد ربه منصور هادي\nرئيس الجمهورية\nتحميل القانون\nعدد الزيارات\n١٤٤٨٢\nعدد التحميلات\n٣٤٨٨",
      "part_number": null,
      "chapter_number": null,
      "division_number": null,
      "subdivision_number": 9
    }
  ],
  "total_articles": 22
}