{
  "source_file": "257_تكليف رؤساء النيابات بالتحقيق والترافع في بعض قضايا المخدرات.docx",
  "source_path": "C:\\Users\\LEGION\\Documents\\kimi\\workspace\\yemen_legal_docs_v5\\التعاميم والكتب الدورية\\257_تكليف رؤساء النيابات بالتحقيق والترافع في بعض قضايا المخدرات.docx",
  "converted_at": "2026-06-23T20:54:40.526514",
  "metadata": {
    "title": "تكليف رؤساء النيابات بالتحقيق والترافع في بعض قضايا المخدرات",
    "classification": "التعاميم والكتب الدورية",
    "number": "٢٥٧",
    "year": "١٩٩٦",
    "source_url": "http://agoyemen.net/lib_details.php?id=257",
    "preamble": "الرقم (م/٣٥٧٢)\nالتاريخ ١٠/١٢/١٩٩٦م\nتعميم رقم ( ) لسنة ١٩٩٦م\nبشأن تكليف رؤساء النيابات بالتحقيق والترافع\nفي بعض قضايا المخدرات\nنظرا للخطورة البالغة التي تشكلها جرائم المخدرات على المجتمع ولضمان عدم إفلات مرتكبيها من توقيع العقوبات القانونية الزاجرة .\nوعليه\nنوجه بتكليف رؤساء النيابات بالتحقيق والترافع في كل قضايا المخدرات المصنفة ضمن الجدول رقم (١) في قانون المخدرات وتقع عليهم مسئولية متابعة تنفيذ الأحكام الصادرة فيها.\n،،،وشكراً،،،\nمحمد علي البدري\nالنائب العام\nتحميل القانون\nعدد الزيارات\n٢٧٧٨\nعدد التحميلات\n١٧٨٢"
  },
  "parts": [],
  "articles": [],
  "flat_articles": [],
  "total_articles": 0
}