{
  "source_file": "312_اعداد ملف مقابل.docx",
  "source_path": "C:\\Users\\LEGION\\Documents\\kimi\\workspace\\yemen_legal_docs_v5\\التعاميم والكتب الدورية\\312_اعداد ملف مقابل.docx",
  "converted_at": "2026-06-23T20:54:41.334007",
  "metadata": {
    "title": "اعداد ملف مقابل",
    "classification": "التعاميم والكتب الدورية",
    "number": "٣١٢",
    "year": "٢٠٠١",
    "source_url": "http://agoyemen.net/lib_details.php?id=312",
    "preamble": "الرقم (٤)\nالتاريخ ٢/٩/٢٠٠١م\nتعميم رقم (٤) لسنة ٢٠٠١م\nبشأن إعداد ملف مقابل\nلما كان قانون الإجراءات الجزائية الصادر بالقرار الجمهوري رقم(١٣) لسنة ١٩٩٤م المادة (٣٤٦/٢،١) منه قد أضاف بعدا جديدا على التشريع حين أوجب اعتماد كاتب المحكمة المختص لمحتويات الملف المقابل المحال من النيابة للمطابقة على الأصل لضمان الحفظ بقوله(تسلم النيابة العامة ملف القضية كاملا لمحكمة الموضوع محتوياً على كافة الأوراق والأدلة والتقارير لمساعدتها على التصرف في القضية.\nوعلى كاتب المحكمة المختص ان يعطي استلام بالملف ومحتوياته لمندوب النيابة العامة على أن يتم اعتماد محتويات الملف المقابل الذي لدى النيابة العامة للمطابقة على الأصل لضمان الحفظ.\nوكانت المادة (٣٣/ج) من التعليمات العامة للنيابة العامة قد أوجبت الاحتفاظ بصورة من ملف القضية المحال إلى المحكمة.\nوحيث ان علة النص القانوني السابق بيانه قد ورد لتمكين النيابة العامة من الاستعانة بالملف المقابل وإمكانية الإشراف والمتابع للقضايا المرسلة إلى المحاكم ومعرفة ما تم فيها من إجراءات ومحافظة على محتويات ملفات القضايا عند فقدان أية وثيقة منها نتيجة تداول الملفات بين النيابات والمحاكم ولتمكين عضو النيابة العامة غير المترافع فيها حين حضور جلسات المحاكمة بدلا عن العضو المترافع من معرفة وقائع الدعوى الجزائية والإطلاع على محتويات ملف القضية لإمكانية تمثيل النيابة العامة أمام المحاكم على الوجه الامثل.\nوحيث لوحظ ان بعض النيابات قد خلا أرشيفها من ملف مقابل لكل قضية تم التصرف فيها بالإحالة إلى المحكمة مخالفة لما توجبه التعليمات العامة للنيابة العامة المادة (٣٣/ج) المتقدم بيانها.\nولأهمية ذلك فإننا نهيب بكافة الأخوة رؤساء النيابة العامة كل في دائرة اختصاصه والإخوة وكلاء النيابة العامة وكافة الأعضاء النيابة العامة إلى مراعاة ذلك بكل دقة.\n،،، والله الموفق،،،\nصدر بمكتب النائب العام\nبتاريخ ١٤/جماد آخر/١٤٢٢ه\nالموافق ٢/٩/٢٠٠١م\nد/عبد الله عبد الله العلفي\nالنائب العام\nتحميل القانون\nعدد الزيارات\n٤٠٣٦\nعدد التحميلات\n١٩٨٦"
  },
  "parts": [],
  "articles": [],
  "flat_articles": [],
  "total_articles": 0
}